refit_loader/__init__.py
refit_loader/data_loader.py
refit_loader/utilities.py
refit_loader/metadata/__init__.py
refit_loader/modules/__init__.py
refit_loader/modules/active_durations.py
refit_loader/modules/parser.py
refit_loader/modules/validations.py
refit_loader-1.2.2.dist-info/LICENSE
refit_loader-1.2.2.dist-info/METADATA
refit_loader-1.2.2.dist-info/WHEEL
refit_loader-1.2.2.dist-info/top_level.txt
refit_loader-1.2.2.dist-info/RECORD
