Metadata-Version: 2.1
Name: refit-loader
Version: 1.2.2
Summary: A simple, fast and handy data loader for REFIT dataset to explore the data at convenience, provided with basic transformations like resampling and extract activities by thresholding.
Author-email: Mahnoor Shahid <mahnoor.shahid.shakir@outlook.com>
License: Copyright (c) 2018 The Python Packaging Authority
Project-URL: repository, https://github.com/mahnoor-shahid/refit_loader
Classifier: Programming Language :: Python :: 3
Classifier: License :: OSI Approved :: MIT License
Classifier: Operating System :: OS Independent
Requires-Python: >=3.9.2
License-File: LICENSE
Requires-Dist: numpy (>=1.20.3)
Requires-Dist: pandas (>=1.2.4)
Requires-Dist: dask (>=2021.06.2)
Requires-Dist: scikit-learn (>=1.1.2)
